editrest/__init__.py
editrest/main.py
editrest/version.py
editrest-0.0.6.dist-info/LICENSE
editrest-0.0.6.dist-info/METADATA
editrest-0.0.6.dist-info/WHEEL
editrest-0.0.6.dist-info/entry_points.txt
editrest-0.0.6.dist-info/top_level.txt
editrest-0.0.6.dist-info/zip-safe
editrest-0.0.6.dist-info/RECORD
