Metadata-Version: 2.1
Name: editrest
Version: 0.0.6
Summary: REST edit: GET + vi + PUT
Home-page: https://github.com/wtnb75/editrest
Author: Watanebe Takashi
Author-email: wtnb75@gmail.com
License: MIT
Classifier: Development Status :: 3 - Alpha
Classifier: Intended Audience :: Developers
Classifier: License :: OSI Approved :: MIT License
Classifier: Topic :: Software Development :: Libraries :: Python Modules
Classifier: Programming Language :: Python :: 3
License-File: LICENSE
Requires-Dist: python-editor
Requires-Dist: requests
Requires-Dist: click
Requires-Dist: toml
Requires-Dist: pyyaml
Requires-Dist: jsonpatch
Provides-Extra: dev
Requires-Dist: pytest ; extra == 'dev'
Requires-Dist: pytest-cov ; extra == 'dev'
Requires-Dist: pytest-md ; extra == 'dev'
Requires-Dist: flake8 ; extra == 'dev'
Requires-Dist: wheel ; extra == 'dev'
Requires-Dist: twine ; extra == 'dev'
Requires-Dist: pyOpenSSL ; extra == 'dev'
